{
  "name": "Galvan Magen",
  "type": "npc",
  "img": "modules/rime-of-the-frostmaiden/assets/actors/Galvan Magen.webp",
  "system": {
    "abilities": {
      "str": {
        "value": 10
      },
      "dex": {
        "value": 18
      },
      "con": {
        "value": 18
      },
      "int": {
        "value": 12
      },
      "wis": {
        "value": 10
      },
      "cha": {
        "value": 7
      }
    },
    "attributes": {
      "ac": {
        "flat": 14,
        "calc": "flat"
      },
      "hp": {
        "value": 68,
        "max": 68,
        "formula": "8d8+32"
      },
      "speed": {
        "value": 30,
        "fly": 30,
        "hover": true
      }
    },
    "details": {
      "type": {
        "value": "construct"
      },
      "alignment": "unaligned",
      "cr": 3,
      "source": "Rime of the Frostmaiden"
    },
    "traits": {
      "languages": {
        "custom": "understands creator's languages but can't speak"
      },
      "di": {
        "value": [
          "lightning",
          "poison"
        ]
      },
      "ci": {
        "value": [
          "charmed",
          "exhaustion",
          "frightened",
          "paralyzed",
          "poisoned"
        ]
      },
      "senses": "passive Perception 10"
    }
  },
  "items": [
    {
      "name": "Fiery End",
      "type": "feat",
      "system": {
        "description": {
          "value": "If the magen dies, its body disintegrates in a harmless burst of fire and smoke."
        }
      },
      "_id": "P6h9BGRRJGhYm4kB",
      "_key": "!actors.items!QMoscjnnuscXWQiI.P6h9BGRRJGhYm4kB",
      "sort": 0,
      "ownership": {
        "default": 0
      },
      "_stats": {
        "coreVersion": "14.363",
        "systemId": "dnd5e",
        "systemVersion": "5.0.3"
      }
    },
    {
      "name": "Magic Resistance",
      "type": "feat",
      "system": {
        "description": {
          "value": "Advantage on saving throws against spells and other magical effects."
        }
      },
      "_id": "z7tsXro7l7hbfHZj",
      "_key": "!actors.items!QMoscjnnuscXWQiI.z7tsXro7l7hbfHZj",
      "sort": 0,
      "ownership": {
        "default": 0
      },
      "_stats": {
        "coreVersion": "14.363",
        "systemId": "dnd5e",
        "systemVersion": "5.0.3"
      }
    },
    {
      "name": "Unusual Nature",
      "type": "feat",
      "system": {
        "description": {
          "value": "Doesn't require air, food, drink, or sleep."
        }
      },
      "_id": "V5eINbsVNSBER9qb",
      "_key": "!actors.items!QMoscjnnuscXWQiI.V5eINbsVNSBER9qb",
      "sort": 0,
      "ownership": {
        "default": 0
      },
      "_stats": {
        "coreVersion": "14.363",
        "systemId": "dnd5e",
        "systemVersion": "5.0.3"
      }
    },
    {
      "name": "Multiattack",
      "type": "feat",
      "system": {
        "description": {
          "value": "Makes two Shocking Touch attacks."
        },
        "activation": {
          "type": "action",
          "cost": 1
        }
      },
      "_id": "AohRs44WwWhRZUjF",
      "_key": "!actors.items!QMoscjnnuscXWQiI.AohRs44WwWhRZUjF",
      "sort": 0,
      "ownership": {
        "default": 0
      },
      "_stats": {
        "coreVersion": "14.363",
        "systemId": "dnd5e",
        "systemVersion": "5.0.3"
      }
    },
    {
      "name": "Shocking Touch",
      "type": "weapon",
      "system": {
        "description": {
          "value": "Melee Spell Attack: +6 to hit, reach 5 ft. Hit: 7 (1d6+4) lightning damage. Advantage if target wears metal armor."
        },
        "activation": {
          "type": "action",
          "cost": 1
        },
        "attackBonus": 6,
        "damage": {
          "parts": [
            [
              "1d6+4",
              "lightning"
            ]
          ]
        }
      },
      "_id": "RM9JVzm79dM9eOdf",
      "_key": "!actors.items!QMoscjnnuscXWQiI.RM9JVzm79dM9eOdf",
      "sort": 0,
      "ownership": {
        "default": 0
      },
      "_stats": {
        "coreVersion": "14.363",
        "systemId": "dnd5e",
        "systemVersion": "5.0.3"
      }
    },
    {
      "name": "Static Discharge (Recharge 5-6)",
      "type": "feat",
      "system": {
        "description": {
          "value": "60-foot line, 5 ft. wide. DC 14 Dexterity save (disadvantage in metal armor) or take 22 (4d10) lightning damage, half on success."
        },
        "activation": {
          "type": "action",
          "cost": 1
        },
        "save": {
          "ability": "dex",
          "dc": 14
        },
        "damage": {
          "parts": [
            [
              "4d10",
              "lightning"
            ]
          ]
        }
      },
      "_id": "wFspH4cTfKQxzz7L",
      "_key": "!actors.items!QMoscjnnuscXWQiI.wFspH4cTfKQxzz7L",
      "sort": 0,
      "ownership": {
        "default": 0
      },
      "_stats": {
        "coreVersion": "14.363",
        "systemId": "dnd5e",
        "systemVersion": "5.0.3"
      }
    }
  ],
  "flags": {
    "rotf": {
      "source": "Appendix C",
      "chapter": "7"
    }
  },
  "prototypeToken": {
    "texture": {
      "src": "https://raw.githubusercontent.com/5etools-mirror-2/5etools-img/main/bestiary/IDRotF/Galvan%20Magen.webp"
    }
  },
  "_id": "QMoscjnnuscXWQiI",
  "_key": "!actors!QMoscjnnuscXWQiI",
  "sort": 0,
  "ownership": {
    "default": 0
  },
  "_stats": {
    "coreVersion": "14.363",
    "systemId": "dnd5e",
    "systemVersion": "5.0.3"
  }
}