{
  "name": "Verbeeg Longstrider",
  "type": "npc",
  "img": "systems/dnd5e/icons/svg/mystery-man.svg",
  "system": {
    "abilities": {
      "str": {
        "value": 19
      },
      "dex": {
        "value": 15
      },
      "con": {
        "value": 16
      },
      "int": {
        "value": 13
      },
      "wis": {
        "value": 14
      },
      "cha": {
        "value": 10
      }
    },
    "attributes": {
      "ac": {
        "flat": 14,
        "calc": "flat",
        "formula": "hide armor"
      },
      "hp": {
        "value": 119,
        "max": 119,
        "formula": "14d10+42"
      },
      "speed": {
        "value": 50
      }
    },
    "details": {
      "type": {
        "value": "giant"
      },
      "alignment": "neutral",
      "cr": 5,
      "source": "Rime of the Frostmaiden"
    },
    "traits": {
      "languages": {
        "value": [
          "common",
          "giant"
        ]
      },
      "senses": "passive Perception 12"
    },
    "saves": {
      "dex": {
        "proficient": 1
      },
      "con": {
        "proficient": 1
      },
      "wis": {
        "proficient": 1
      }
    },
    "skills": {
      "ani": {
        "value": 1
      },
      "ath": {
        "value": 2
      },
      "ste": {
        "value": 1
      }
    }
  },
  "items": [
    {
      "name": "Innate Spellcasting",
      "type": "feat",
      "system": {
        "description": {
          "value": "Spellcasting ability Wisdom. 1/day each: animal messenger, fog cloud, freedom of movement, pass without trace, silence, water walk."
        }
      },
      "_id": "KekEOYhlXlyTEKKl",
      "_key": "!actors.items!lbmUa5dBoJdDiIIu.KekEOYhlXlyTEKKl",
      "sort": 0,
      "ownership": {
        "default": 0
      },
      "_stats": {
        "coreVersion": "14.364",
        "systemId": "dnd5e",
        "systemVersion": "5.0.3"
      }
    },
    {
      "name": "Simple Weapon Wielder",
      "type": "feat",
      "system": {
        "description": {
          "value": "A simple weapon deals one extra die of its damage when the verbeeg hits with it."
        }
      },
      "_id": "6t0LRiuLhrASBZ7I",
      "_key": "!actors.items!lbmUa5dBoJdDiIIu.6t0LRiuLhrASBZ7I",
      "sort": 0,
      "ownership": {
        "default": 0
      },
      "_stats": {
        "coreVersion": "14.364",
        "systemId": "dnd5e",
        "systemVersion": "5.0.3"
      }
    },
    {
      "name": "Multiattack",
      "type": "feat",
      "system": {
        "description": {
          "value": "Makes two melee attacks."
        },
        "activation": {
          "type": "action",
          "cost": 1
        }
      },
      "_id": "RvC2YgjHEWMPlWyX",
      "_key": "!actors.items!lbmUa5dBoJdDiIIu.RvC2YgjHEWMPlWyX",
      "sort": 0,
      "ownership": {
        "default": 0
      },
      "_stats": {
        "coreVersion": "14.364",
        "systemId": "dnd5e",
        "systemVersion": "5.0.3"
      }
    },
    {
      "name": "Spear",
      "type": "weapon",
      "system": {
        "description": {
          "value": "Melee or Ranged: +7 to hit, reach 5 ft. or range 20/60 ft. Hit: 14 (3d6+4) piercing, or 17 (3d8+4) if ranged or two-handed."
        },
        "activation": {
          "type": "action",
          "cost": 1
        },
        "attackBonus": 7,
        "damage": {
          "parts": [
            [
              "3d6+4",
              "piercing"
            ]
          ]
        }
      },
      "_id": "WxCRm77r5eyCnDYp",
      "_key": "!actors.items!lbmUa5dBoJdDiIIu.WxCRm77r5eyCnDYp",
      "sort": 0,
      "ownership": {
        "default": 0
      },
      "_stats": {
        "coreVersion": "14.364",
        "systemId": "dnd5e",
        "systemVersion": "5.0.3"
      }
    },
    {
      "name": "Sling",
      "type": "weapon",
      "system": {
        "description": {
          "value": "Ranged: +5 to hit, range 30/120 ft. Hit: 9 (3d4+2) bludgeoning. DC 15 Constitution save or stunned until end of its next turn."
        },
        "activation": {
          "type": "action",
          "cost": 1
        },
        "attackBonus": 5,
        "damage": {
          "parts": [
            [
              "3d4+2",
              "bludgeoning"
            ]
          ]
        }
      },
      "_id": "i8WcEOVVI5nh7bRC",
      "_key": "!actors.items!lbmUa5dBoJdDiIIu.i8WcEOVVI5nh7bRC",
      "sort": 0,
      "ownership": {
        "default": 0
      },
      "_stats": {
        "coreVersion": "14.364",
        "systemId": "dnd5e",
        "systemVersion": "5.0.3"
      }
    }
  ],
  "flags": {
    "rotf": {
      "source": "Appendix C",
      "chapter": "2"
    }
  },
  "_id": "lbmUa5dBoJdDiIIu",
  "_key": "!actors!lbmUa5dBoJdDiIIu",
  "sort": 0,
  "ownership": {
    "default": 0
  },
  "_stats": {
    "coreVersion": "14.364",
    "systemId": "dnd5e",
    "systemVersion": "5.0.3"
  },
  "effects": [],
  "folder": null,
  "prototypeToken": {
    "name": "Verbeeg Longstrider",
    "img": "systems/dnd5e/icons/svg/mystery-man.svg",
    "displayName": 0,
    "displayBars": 0,
    "actorLink": false,
    "disposition": -1,
    "bar1": {
      "attribute": "attributes.hp"
    },
    "bar2": {
      "attribute": null
    },
    "flags": {}
  }
}