{
  "name": "Yeti Tyke",
  "type": "npc",
  "img": "systems/dnd5e/icons/svg/mystery-man.svg",
  "system": {
    "abilities": {
      "str": {
        "value": 10
      },
      "dex": {
        "value": 11
      },
      "con": {
        "value": 12
      },
      "int": {
        "value": 6
      },
      "wis": {
        "value": 8
      },
      "cha": {
        "value": 5
      }
    },
    "attributes": {
      "ac": {
        "flat": 11,
        "calc": "flat",
        "formula": "natural armor"
      },
      "hp": {
        "value": 9,
        "max": 9,
        "formula": "2d6+2"
      },
      "speed": {
        "value": 20,
        "climb": 20
      }
    },
    "details": {
      "type": {
        "value": "monstrosity"
      },
      "alignment": "chaotic evil",
      "cr": 0.125,
      "source": "Rime of the Frostmaiden"
    },
    "traits": {
      "languages": {
        "custom": "understands Yeti but can't speak"
      },
      "di": {
        "value": [
          "cold"
        ]
      },
      "senses": "darkvision 60 ft., passive Perception 9"
    }
  },
  "items": [
    {
      "name": "Keen Smell",
      "type": "feat",
      "system": {
        "description": {
          "value": "Advantage on Wisdom (Perception) checks that rely on smell."
        }
      },
      "_id": "rEwFnfVOizOuRwoI",
      "_key": "!actors.items!nb2r0S78m5r0Gu2i.rEwFnfVOizOuRwoI",
      "sort": 0,
      "ownership": {
        "default": 0
      },
      "_stats": {
        "coreVersion": "14.364",
        "systemId": "dnd5e",
        "systemVersion": "5.0.3"
      }
    },
    {
      "name": "Snow Camouflage",
      "type": "feat",
      "system": {
        "description": {
          "value": "Advantage on Dexterity (Stealth) checks in snowy terrain."
        }
      },
      "_id": "BiIc1BuQUNZwPGDJ",
      "_key": "!actors.items!nb2r0S78m5r0Gu2i.BiIc1BuQUNZwPGDJ",
      "sort": 0,
      "ownership": {
        "default": 0
      },
      "_stats": {
        "coreVersion": "14.364",
        "systemId": "dnd5e",
        "systemVersion": "5.0.3"
      }
    },
    {
      "name": "Claw",
      "type": "weapon",
      "system": {
        "description": {
          "value": "Melee: +2 to hit, reach 5 ft. Hit: 2 (1d4) slashing plus 2 (1d4) cold damage."
        },
        "activation": {
          "type": "action",
          "cost": 1
        },
        "attackBonus": 2,
        "damage": {
          "parts": [
            [
              "1d4",
              "slashing"
            ],
            [
              "1d4",
              "cold"
            ]
          ]
        }
      },
      "_id": "AaJtG86stHDEsSYB",
      "_key": "!actors.items!nb2r0S78m5r0Gu2i.AaJtG86stHDEsSYB",
      "sort": 0,
      "ownership": {
        "default": 0
      },
      "_stats": {
        "coreVersion": "14.364",
        "systemId": "dnd5e",
        "systemVersion": "5.0.3"
      }
    }
  ],
  "flags": {
    "rotf": {
      "source": "Appendix C",
      "chapter": "various"
    }
  },
  "prototypeToken": {
    "texture": {
      "src": "https://raw.githubusercontent.com/5etools-mirror-2/5etools-img/main/bestiary/IDRotF/Yeti%20Tyke.webp"
    },
    "name": "Yeti Tyke",
    "img": "systems/dnd5e/icons/svg/mystery-man.svg",
    "displayName": 0,
    "displayBars": 0,
    "actorLink": false,
    "disposition": -1,
    "bar1": {
      "attribute": "attributes.hp"
    },
    "bar2": {
      "attribute": null
    },
    "flags": {}
  },
  "_id": "nb2r0S78m5r0Gu2i",
  "_key": "!actors!nb2r0S78m5r0Gu2i",
  "sort": 0,
  "ownership": {
    "default": 0
  },
  "_stats": {
    "coreVersion": "14.364",
    "systemId": "dnd5e",
    "systemVersion": "5.0.3"
  },
  "effects": [],
  "folder": null
}